loadforecast/__init__.py
loadforecast/forecaster.py
loadforecast/model_load.py
loadforecast/surpress_output.py
loadforecast/warm_start.py
loadforecast-0.0.4.dist-info/LICENSE
loadforecast-0.0.4.dist-info/METADATA
loadforecast-0.0.4.dist-info/WHEEL
loadforecast-0.0.4.dist-info/top_level.txt
loadforecast-0.0.4.dist-info/RECORD
