Metadata-Version: 2.1
Name: loadforecast
Version: 0.0.4
Summary: A package for easy time series forecasting of electrical load
Home-page: https://github.com/MarekWadinger/loadforecast
Author: Marek Wadinger
Author-email: marekwadinger5506@gmail.com
License: UNKNOWN
Project-URL: Bug Tracker, https://github.com/MarekWadinger/loadforecast/issues
Platform: UNKNOWN
Classifier: Programming Language :: Python :: 3
Classifier: License :: OSI Approved :: MIT License
Classifier: Operating System :: OS Independent
Requires-Python: >=3.8
